odoo/addons/web_time_range_menu_custom/README.rst
odoo/addons/web_time_range_menu_custom/__init__.py
odoo/addons/web_time_range_menu_custom/__manifest__.py
odoo/addons/web_time_range_menu_custom/i18n/web_time_range_menu_custom.pot
odoo/addons/web_time_range_menu_custom/readme/CONTRIBUTORS.rst
odoo/addons/web_time_range_menu_custom/readme/DESCRIPTION.rst
odoo/addons/web_time_range_menu_custom/static/description/icon.png
odoo/addons/web_time_range_menu_custom/static/description/index.html
odoo/addons/web_time_range_menu_custom/static/src/js/control_panel_controller.js
odoo/addons/web_time_range_menu_custom/static/src/js/control_panel_model.js
odoo/addons/web_time_range_menu_custom/static/src/js/control_panel_view_parameters.js
odoo/addons/web_time_range_menu_custom/static/src/js/domain.js
odoo/addons/web_time_range_menu_custom/static/src/js/search_facet.js
odoo/addons/web_time_range_menu_custom/static/src/js/time_range_menu.js
odoo/addons/web_time_range_menu_custom/static/src/xml/time_range_menu.xml
odoo/addons/web_time_range_menu_custom/templates/assets.xml
odoo13_addon_web_time_range_menu_custom-13.0.1.0.1.dist-info/METADATA
odoo13_addon_web_time_range_menu_custom-13.0.1.0.1.dist-info/WHEEL
odoo13_addon_web_time_range_menu_custom-13.0.1.0.1.dist-info/top_level.txt
odoo13_addon_web_time_range_menu_custom-13.0.1.0.1.dist-info/RECORD
